mapper/__init__.py
mapper/casedict.py
mapper/object_mapper.py
mapper/object_mapper_exception.py
tests/__init__.py
tests/object_mapper_test.py
object_mapper-1.0.7.dist-info/LICENSE
object_mapper-1.0.7.dist-info/LICENSE.txt
object_mapper-1.0.7.dist-info/METADATA
object_mapper-1.0.7.dist-info/WHEEL
object_mapper-1.0.7.dist-info/top_level.txt
object_mapper-1.0.7.dist-info/RECORD
