Metadata-Version: 2.1
Name: object-mapper
Version: 1.0.7
Summary: ObjectMapper is a class for automatic object mapping. It helps you to create objects between                project layers (data layer, service layer, view) in a simple, transparent way.
Home-page: https://github.com/marazt/object-mapper
Author: marazt
Author-email: marazt@gmail.com
License: MIT
Keywords: utils dto object-mapper mapping development
Platform: UNKNOWN
Classifier: Development Status :: 5 - Production/Stable
Classifier: Intended Audience :: Developers
Classifier: Topic :: Software Development :: Build Tools
Classifier: License :: OSI Approved :: MIT License
Classifier: Programming Language :: Python :: 2
Classifier: Programming Language :: Python :: 2.7
Classifier: Programming Language :: Python :: 3
Classifier: Programming Language :: Python :: 3.3
Classifier: Programming Language :: Python :: 3.4
Classifier: Programming Language :: Python :: 3.5
Classifier: Programming Language :: Python :: 3.6
Requires-Dist: datetime
Requires-Dist: nose
Provides-Extra: dev
Provides-Extra: test
Requires-Dist: nose ; extra == 'test'
